odoo/addons/auth_totp_password_security/README.rst
odoo/addons/auth_totp_password_security/__init__.py
odoo/addons/auth_totp_password_security/__manifest__.py
odoo/addons/auth_totp_password_security/controllers/__init__.py
odoo/addons/auth_totp_password_security/controllers/main.py
odoo/addons/auth_totp_password_security/i18n/auth_totp_password_security.pot
odoo/addons/auth_totp_password_security/static/description/icon.png
odoo/addons/auth_totp_password_security/tests/__init__.py
odoo/addons/auth_totp_password_security/tests/test_main.py
odoo12_addon_auth_totp_password_security-12.0.1.0.0.99.dev1.dist-info/METADATA
odoo12_addon_auth_totp_password_security-12.0.1.0.0.99.dev1.dist-info/WHEEL
odoo12_addon_auth_totp_password_security-12.0.1.0.0.99.dev1.dist-info/top_level.txt
odoo12_addon_auth_totp_password_security-12.0.1.0.0.99.dev1.dist-info/RECORD
